test123plz/__init__.py
test123plz/test.py
test123plz-0.1.1.dist-info/METADATA
test123plz-0.1.1.dist-info/WHEEL
test123plz-0.1.1.dist-info/RECORD
