Metadata-Version: 2.4
Name: test123plz
Version: 0.1.1
Summary: pico comm test
Author-email: adam <adamzidani.az@gmail.com>
Classifier: Operating System :: OS Independent
Classifier: Programming Language :: Python :: 3
Requires-Python: >=3.9
